pyroostermoney/__init__.py
pyroostermoney/api.py
pyroostermoney/const.py
pyroostermoney/enum.py
pyroostermoney/events.py
pyroostermoney/exceptions.py
pyroostermoney/family_account.py
pyroostermoney/master_jobs.py
pyroostermoney/roostermoney.py
pyroostermoney/child/__init__.py
pyroostermoney/child/card.py
pyroostermoney/child/jobs.py
pyroostermoney/child/money_pot.py
pyroostermoney/child/standing_order.py
pyroostermoney/child/transaction.py
pyroostermoney-2023.12.1.dist-info/LICENSE
pyroostermoney-2023.12.1.dist-info/METADATA
pyroostermoney-2023.12.1.dist-info/WHEEL
pyroostermoney-2023.12.1.dist-info/top_level.txt
pyroostermoney-2023.12.1.dist-info/RECORD
