Metadata-Version: 2.1
Name: pyroostermoney
Version: 2023.12.1
Summary: A RoosterMoney integration for Python.
Home-page: https://github.com/pantherale0/pyroostermoney
Author: pantherale0
Author-email: support@system32.uk
License: MIT
Project-URL: Bug Tracker, https://github.com/pantherale0/pyroostermoney/issues
Project-URL: Changelog, https://github.com/pantherale0/pyroostermoney/releases
Classifier: Programming Language :: Python :: 3
Classifier: License :: OSI Approved :: BSD License
Classifier: Intended Audience :: Developers
License-File: LICENSE
Requires-Dist: aiohttp
